uddup/__init__.py
uddup/main.py
uddup-0.9.3.dist-info/LICENSE.md
uddup-0.9.3.dist-info/METADATA
uddup-0.9.3.dist-info/WHEEL
uddup-0.9.3.dist-info/entry_points.txt
uddup-0.9.3.dist-info/top_level.txt
uddup-0.9.3.dist-info/RECORD
