Metadata-Version: 2.1
Name: uddup
Version: 0.9.3
Summary: URLs Deduplication Tool.
Home-page: https://github.com/rotemreiss/uddup
Author: Rotem Reiss
Author-email: reiss.r@gmail.com
License: UNKNOWN
Platform: UNKNOWN
Classifier: Programming Language :: Python :: 3
Classifier: License :: OSI Approved :: MIT License
Classifier: Operating System :: OS Independent
